Watchmen/__init__.py
Watchmen/python.py
Watchmen/robotframework.py
Watchmen-0.2.9.dist-info/LICENSE
Watchmen-0.2.9.dist-info/METADATA
Watchmen-0.2.9.dist-info/WHEEL
Watchmen-0.2.9.dist-info/top_level.txt
Watchmen-0.2.9.dist-info/RECORD
