Metadata-Version: 2.1
Name: Watchmen
Version: 0.2.9
Summary: Comparing Image for Tesena
Home-page: https://github.com/procesor2017/watchmen
Author: Procesor
Author-email: jfortik@gmail.com
License: UNKNOWN
Platform: UNKNOWN
Classifier: Programming Language :: Python :: 3.6
Classifier: License :: OSI Approved :: MIT License
Classifier: Operating System :: OS Independent
Requires-Python: >3.6
Requires-Dist: Pillow
Requires-Dist: numpy
Requires-Dist: scikit-image
Requires-Dist: imutils
Requires-Dist: opencv-python
Requires-Dist: robotframework
